[
  {
    "id": 1,
    "title": "Nature 1",
    "url": "https://www.w3schools.com/html/mov_bbb.mp4",
    "likes": 25,
    "shares": 3
  },
  {
    "id": 2,
    "title": "Nature 2",
    "url": "https://www.w3schools.com/html/movie.mp4",
    "likes": 18,
    "shares": 5
  },
  {
    "id": 3,
    "title": "Travel 1",
    "url": "https://www.w3schools.com/html/mov_bbb.mp4",
    "likes": 45,
    "shares": 9
  },
  {
    "id": 4,
    "title": "Travel 2",
    "url": "https://www.w3schools.com/html/movie.mp4",
    "likes": 32,
    "shares": 7
  },
  {
    "id": 5,
    "title": "Food 1",
    "url": "https://www.w3schools.com/html/mov_bbb.mp4",
    "likes": 14,
    "shares": 2
  },
  {
    "id": 6,
    "title": "Food 2",
    "url": "https://www.w3schools.com/html/movie.mp4",
    "likes": 55,
    "shares": 12
  },
  {
    "id": 7,
    "title": "Sports 1",
    "url": "https://www.w3schools.com/html/mov_bbb.mp4",
    "likes": 29,
    "shares": 4
  },
  {
    "id": 8,
    "title": "Sports 2",
    "url": "https://www.w3schools.com/html/movie.mp4",
    "likes": 61,
    "shares": 11
  },
  {
    "id": 9,
    "title": "Music 1",
    "url": "https://www.w3schools.com/html/mov_bbb.mp4",
    "likes": 72,
    "shares": 20
  },
  {
    "id": 10,
    "title": "Music 2",
    "url": "https://www.w3schools.com/html/movie.mp4",
    "likes": 38,
    "shares": 6
  },
  {
    "id": 11,
    "title": "Lifestyle 1",
    "url": "https://www.w3schools.com/html/mov_bbb.mp4",
    "likes": 41,
    "shares": 8
  },
  {
    "id": 12,
    "title": "Lifestyle 2",
    "url": "https://www.w3schools.com/html/movie.mp4",
    "likes": 22,
    "shares": 3
  },
  {
    "id": 13,
    "title": "Adventure 1",
    "url": "https://www.w3schools.com/html/mov_bbb.mp4",
    "likes": 80,
    "shares": 15
  },
  {
    "id": 14,
    "title": "Adventure 2",
    "url": "https://www.w3schools.com/html/movie.mp4",
    "likes": 47,
    "shares": 10
  },
  {
    "id": 15,
    "title": "City Life",
    "url": "https://www.w3schools.com/html/mov_bbb.mp4",
    "likes": 36,
    "shares": 5
  }
]